wmtex.py
wm_tex-1.0.5.dist-info/METADATA
wm_tex-1.0.5.dist-info/WHEEL
wm_tex-1.0.5.dist-info/entry_points.txt
wm_tex-1.0.5.dist-info/top_level.txt
wm_tex-1.0.5.dist-info/RECORD
