Metadata-Version: 2.4
Name: wm-tex
Version: 1.0.5
Summary: Automatically reference a URL with the Wayback Machine in BibTeX
Keywords: wayback,bibtex,latex,bibliography
Requires-Python: >=3.12
Requires-Dist: waybackpy==3.0.6
